apparatusai/__init__.py
apparatusai/client.py
apparatusai-1.0.0.dist-info/METADATA
apparatusai-1.0.0.dist-info/WHEEL
apparatusai-1.0.0.dist-info/top_level.txt
apparatusai-1.0.0.dist-info/RECORD
