Metadata-Version: 2.2
Name: apparatusai
Version: 1.0.0
Summary: Python SDK for ApparatusAI
Home-page: https://github.com/comethrusws/apparatusai-sdk
Author: Basab Jha
Author-email: basab@apparatusai.space
Classifier: Programming Language :: Python :: 3
Classifier: License :: OSI Approved :: MIT License
Classifier: Operating System :: OS Independent
Requires-Dist: requests>=2.25.1
Dynamic: author
Dynamic: author-email
Dynamic: classifier
Dynamic: description
Dynamic: description-content-type
Dynamic: home-page
Dynamic: requires-dist
Dynamic: summary
